comp128/__init__.py
comp128/comp128v1.py
comp128/comp128v23.py
comp128-1.0.0.dist-info/LICENSE
comp128-1.0.0.dist-info/METADATA
comp128-1.0.0.dist-info/WHEEL
comp128-1.0.0.dist-info/top_level.txt
comp128-1.0.0.dist-info/RECORD
