Metadata-Version: 2.2
Name: comp128
Version: 1.0.0
Summary: A Python implementation of the COMP128 GSM authentication algorithms.
Author-email: Lennart Rosam <hello@takuto.de>
Maintainer-email: Lennart Rosam <hello@takuto.de>
License: GPL-2.0-or-later
Project-URL: Repository, https://github.com/Takuto88/comp128-python.git
Project-URL: HomePage, https://github.com/Takuto88/comp128-python
Keywords: comp128,gsm,2g,authentication,algorithms,crypto,cryptography
Classifier: Development Status :: 5 - Production/Stable
Classifier: Intended Audience :: Developers
Classifier: License :: OSI Approved :: GNU General Public License v2 or later (GPLv2+)
Classifier: Programming Language :: Python :: 3.7
Classifier: Programming Language :: Python :: 3.8
Classifier: Programming Language :: Python :: 3.9
Classifier: Programming Language :: Python :: 3.10
Classifier: Programming Language :: Python :: 3.11
Classifier: Programming Language :: Python :: 3.12
Classifier: Programming Language :: Python :: 3.13
Classifier: Programming Language :: Python :: 3 :: Only
Classifier: Topic :: Software Development :: Libraries :: Python Modules
Classifier: Topic :: Security :: Cryptography
Requires-Python: >=3.7
License-File: LICENSE
Provides-Extra: dev
Requires-Dist: parameterized>=0.7.2; extra == "dev"
